mcp_server/__init__.py
mcp_server/config.py
mcp_server/server.py
mcp_server/wecom_client.py
hitl_mcp-0.2.1.dist-info/METADATA
hitl_mcp-0.2.1.dist-info/WHEEL
hitl_mcp-0.2.1.dist-info/entry_points.txt
hitl_mcp-0.2.1.dist-info/RECORD
