Metadata-Version: 2.4
Name: hitl-mcp
Version: 0.2.1
Summary: Human-in-the-Loop MCP Server for WeCom (企业微信) - 让 AI 能够与人类实时交互
Project-URL: Homepage, https://github.com/user/hitl-mcp
Project-URL: Repository, https://github.com/user/hitl-mcp
Author: Kong Jie
License: MIT
Keywords: ai,claude,human-in-the-loop,mcp,wecom
Classifier: Development Status :: 4 - Beta
Classifier: Intended Audience :: Developers
Classifier: License :: OSI Approved :: MIT License
Classifier: Programming Language :: Python :: 3
Classifier: Programming Language :: Python :: 3.10
Classifier: Programming Language :: Python :: 3.11
Classifier: Programming Language :: Python :: 3.12
Classifier: Topic :: Communications :: Chat
Classifier: Topic :: Scientific/Engineering :: Artificial Intelligence
Requires-Python: >=3.10
Requires-Dist: httpx>=0.27.0
Requires-Dist: mcp>=1.0.0
Requires-Dist: pydantic-settings>=2.0.0
Requires-Dist: pydantic>=2.0.0
